[{"model": "cerfa_filler.companylegalforms", "pk": 1, "fields": {"code": "0", "label": "Organisme de placement collectif en valeurs mobilières sans personnalité morale"}}, {"model": "cerfa_filler.companylegalforms", "pk": 2, "fields": {"code": "10", "label": "Entrepreneur individuel"}}, {"model": "cerfa_filler.companylegalforms", "pk": 3, "fields": {"code": "21", "label": "Indivision"}}, {"model": "cerfa_filler.companylegalforms", "pk": 4, "fields": {"code": "22", "label": "Société créée de fait"}}, {"model": "cerfa_filler.companylegalforms", "pk": 5, "fields": {"code": "23", "label": "Société en participation"}}, {"model": "cerfa_filler.companylegalforms", "pk": 6, "fields": {"code": "24", "label": "Fiducie "}}, {"model": "cerfa_filler.companylegalforms", "pk": 7, "fields": {"code": "27", "label": "Paroisse hors zone concordataire"}}, {"model": "cerfa_filler.companylegalforms", "pk": 8, "fields": {"code": "28", "label": "Assujetti unique à la TVA"}}, {"model": "cerfa_filler.companylegalforms", "pk": 9, "fields": {"code": "29", "label": "Autre groupement de droit privé non doté de la personnalité morale"}}, {"model": "cerfa_filler.companylegalforms", "pk": 10, "fields": {"code": "31", "label": "Personne morale de droit étranger, immatriculée au RCS (registre du commerce et des sociétés)"}}, {"model": "cerfa_filler.companylegalforms", "pk": 11, "fields": {"code": "32", "label": "Personne morale de droit étranger, non immatriculée au RCS"}}, {"model": "cerfa_filler.companylegalforms", "pk": 12, "fields": {"code": "41", "label": "Etablissement public ou régie à caractère industriel ou commercial"}}, {"model": "cerfa_filler.companylegalforms", "pk": 13, "fields": {"code": "51", "label": "Société coopérative commerciale particulière"}}, {"model": "cerfa_filler.companylegalforms", "pk": 14, "fields": {"code": "52", "label": "Société en nom collectif"}}, {"model": "cerfa_filler.companylegalforms", "pk": 15, "fields": {"code": "53", "label": "Société en commandite"}}, {"model": "cerfa_filler.companylegalforms", "pk": 16, "fields": {"code": "54", "label": "Société à responsabilité limitée (SARL)"}}, {"model": "cerfa_filler.companylegalforms", "pk": 17, "fields": {"code": "55", "label": "Société anonyme à conseil d'administration"}}, {"model": "cerfa_filler.companylegalforms", "pk": 18, "fields": {"code": "56", "label": "Société anonyme à directoire"}}, {"model": "cerfa_filler.companylegalforms", "pk": 19, "fields": {"code": "57", "label": "Société par actions simplifiée"}}, {"model": "cerfa_filler.companylegalforms", "pk": 20, "fields": {"code": "58", "label": "Société européenne "}}, {"model": "cerfa_filler.companylegalforms", "pk": 21, "fields": {"code": "61", "label": "Caisse d'épargne et de prévoyance"}}, {"model": "cerfa_filler.companylegalforms", "pk": 22, "fields": {"code": "62", "label": "Groupement d'intérêt économique"}}, {"model": "cerfa_filler.companylegalforms", "pk": 23, "fields": {"code": "63", "label": "Société coopérative agricole"}}, {"model": "cerfa_filler.companylegalforms", "pk": 24, "fields": {"code": "64", "label": "Société d'assurance mutuelle"}}, {"model": "cerfa_filler.companylegalforms", "pk": 25, "fields": {"code": "65", "label": "Société civile"}}, {"model": "cerfa_filler.companylegalforms", "pk": 26, "fields": {"code": "69", "label": "Autre personne morale de droit privé inscrite au registre du commerce et des sociétés"}}, {"model": "cerfa_filler.companylegalforms", "pk": 27, "fields": {"code": "71", "label": "Administration de l'état"}}, {"model": "cerfa_filler.companylegalforms", "pk": 28, "fields": {"code": "72", "label": "Collectivité territoriale"}}, {"model": "cerfa_filler.companylegalforms", "pk": 29, "fields": {"code": "73", "label": "Etablissement public administratif"}}, {"model": "cerfa_filler.companylegalforms", "pk": 30, "fields": {"code": "74", "label": "Autre personne morale de droit public administratif"}}, {"model": "cerfa_filler.companylegalforms", "pk": 31, "fields": {"code": "81", "label": "Organisme gérant un régime de protection sociale à adhésion obligatoire"}}, {"model": "cerfa_filler.companylegalforms", "pk": 32, "fields": {"code": "82", "label": "Organisme mutualiste"}}, {"model": "cerfa_filler.companylegalforms", "pk": 33, "fields": {"code": "83", "label": "Comité d'entreprise"}}, {"model": "cerfa_filler.companylegalforms", "pk": 34, "fields": {"code": "84", "label": "Organisme professionnel"}}, {"model": "cerfa_filler.companylegalforms", "pk": 35, "fields": {"code": "85", "label": "Organisme de retraite à adhésion non obligatoire"}}, {"model": "cerfa_filler.companylegalforms", "pk": 36, "fields": {"code": "91", "label": "Syndicat de propriétaires"}}, {"model": "cerfa_filler.companylegalforms", "pk": 37, "fields": {"code": "92", "label": "Association loi 1901 ou assimilé"}}, {"model": "cerfa_filler.companylegalforms", "pk": 38, "fields": {"code": "93", "label": "Fondation"}}, {"model": "cerfa_filler.companylegalforms", "pk": 39, "fields": {"code": "99", "label": "Autre personne morale de droit privé"}}]